jacob_comeau/__init__.py
jacob_comeau/functions.py
jacob_comeau-0.1.0.dist-info/METADATA
jacob_comeau-0.1.0.dist-info/WHEEL
jacob_comeau-0.1.0.dist-info/top_level.txt
jacob_comeau-0.1.0.dist-info/RECORD
